idle_cn/__init__.py
idle_cn-1.0.dist-info/METADATA
idle_cn-1.0.dist-info/WHEEL
idle_cn-1.0.dist-info/top_level.txt
idle_cn-1.0.dist-info/RECORD
