Metadata-Version: 2.1
Name: idle-cn
Version: 1.0
Summary: IDLE汉化管理器
Home-page: https://github.com/YHL12345656/idle_cn
License: UNKNOWN
Platform: UNKNOWN
Requires-Python: >=3.0.0
